{
  "Version": 3,
  "Meta": {
    "Duration": 9.0,
    "Fps": 30.0,
    "Loop": true,
    "AreBeziersRestricted": true,
    "CurveCount": 89,
    "TotalSegmentCount": 279,
    "TotalPointCount": 469,
    "UserDataCount": 1,
    "TotalUserDataSize": 0
  },
  "Curves": [
    {
      "Target": "Parameter",
      "Id": "ParamEyeLOpen",
      "Segments": [
        0,
        0.75,
        2,
        3,
        0.75,
        0,
        3.333,
        0,
        0,
        3.833,
        0.75,
        2,
        6.967,
        0.75,
        0,
        7.4,
        0,
        2,
        8.133,
        0,
        1,
        8.422,
        0,
        8.711,
        0.695,
        9,
        0.747
      ]
    },
    {
      "Target": "Parameter",
      "Id": "ParamEyeLSmile",
      "Segments": [
        0,
        0.5,
        2,
        2.7,
        0.5,
        0,
        4.033,
        0.3,
        0,
        6.733,
        0.5,
        0,
        7.533,
        0.2,
        2,
        8.267,
        0.2,
        1,
        8.511,
        0.2,
        8.756,
        0.474,
        9,
        0.498
      ]
    },
    {
      "Target": "Parameter",
      "Id": "ParamEyeROpen",
      "Segments": [
        0,
        0.75,
        2,
        3,
        0.75,
        0,
        3.333,
        0,
        0,
        3.833,
        0.75,
        2,
        6.967,
        0.75,
        0,
        7.4,
        0,
        2,
        8.133,
        0,
        1,
        8.422,
        0,
        8.711,
        0.695,
        9,
        0.747
      ]
    },
    {
      "Target": "Parameter",
      "Id": "ParamEyeRSmile",
      "Segments": [
        0,
        0.5,
        2,
        2.7,
        0.5,
        0,
        4.033,
        0.3,
        0,
        6.733,
        0.5,
        0,
        7.533,
        0,
        2,
        8.267,
        0,
        1,
        8.511,
        0,
        8.756,
        0.457,
        9,
        0.497
      ]
    },
    {
      "Target": "Parameter",
      "Id": "ParamEyeBallX",
      "Segments": [
        0,
        0,
        2,
        0.633,
        0,
        2,
        2.1,
        0,
        2,
        3.3,
        0,
        0,
        4.1,
        -0.3,
        2,
        5.2,
        -0.3,
        0,
        6.367,
        0.2,
        1,
        7.245,
        0.2,
        8.122,
        0.005,
        9,
        0
      ]
    },
    {
      "Target": "Parameter",
      "Id": "ParamEyeBallY",
      "Segments": [
        0,
        0,
        2,
        0.633,
        0,
        0,
        2.1,
        0.4,
        1,
        2.5,
        0.4,
        2.9,
        0.16,
        3.3,
        0,
        1,
        3.567,
        -0.107,
        3.833,
        -0.1,
        4.1,
        -0.1,
        2,
        5.2,
        -0.1,
        0,
        6.367,
        0,
        2,
        9,
        0
      ]
    },
    {
      "Target": "Parameter",
      "Id": "ParamMouthForm",
      "Segments": [
        0,
        0,
        1,
        0.511,
        0,
        1.022,
        0.747,
        1.533,
        0.8,
        1,
        3.166,
        0.971,
        4.8,
        1,
        6.433,
        1,
        1,
        7.289,
        1,
        8.144,
        0.025,
        9,
        0
      ]
    },
    {
      "Target": "Parameter",
      "Id": "ParamMouthX",
      "Segments": [
        0,
        0,
        2,
        1,
        0,
        0,
        2.667,
        1,
        2,
        6.733,
        1,
        1,
        7.489,
        1,
        8.244,
        0.029,
        9,
        0.001
      ]
    },
    {
      "Target": "Parameter",
      "Id": "ParamMouthOpenY",
      "Segments": [
        0,
        0,
        0,
        1.067,
        1,
        2,
        1.833,
        1,
        0,
        5.267,
        0.5,
        0,
        8,
        1,
        1,
        8.333,
        1,
        8.667,
        0.063,
        9,
        0.003
      ]
    },
    {
      "Target": "Parameter",
      "Id": "ParamArmL",
      "Segments": [
        0,
        0,
        1,
        0.989,
        1.491,
        1.978,
        1.316,
        2.967,
        1.316,
        0,
        5,
        -6.275,
        1,
        6.333,
        -6.275,
        7.667,
        -2.097,
        9,
        -0.051
      ]
    },
    {
      "Target": "Parameter",
      "Id": "ParamArmL1",
      "Segments": [
        0,
        0,
        0,
        1.733,
        -4.778,
        0,
        4.033,
        22.457,
        0,
        5.833,
        0,
        2,
        9,
        0
      ]
    },
    {
      "Target": "Parameter",
      "Id": "ParamArmL1Y",
      "Segments": [
        0,
        0,
        1,
        0.578,
        0,
        1.155,
        1.231,
        1.733,
        4,
        1,
        1.766,
        4.16,
        1.8,
        5.17,
        1.833,
        5.492,
        1,
        2.711,
        13.969,
        3.589,
        18.042,
        4.467,
        18.042,
        0,
        6.267,
        0,
        2,
        7.4,
        0,
        2,
        9,
        0
      ]
    },
    {
      "Target": "Parameter",
      "Id": "ParamHandL",
      "Segments": [
        0,
        0,
        0,
        1.233,
        9.212,
        0,
        2.933,
        -11.176,
        0,
        5.567,
        4,
        1,
        6.711,
        4,
        7.856,
        0.077,
        9,
        0.001
      ]
    },
    {
      "Target": "Parameter",
      "Id": "ParamFingerL1",
      "Segments": [
        0,
        -30,
        0,
        3.2,
        -1.28,
        0,
        4.767,
        -25.054,
        0,
        6.933,
        -8.962,
        2,
        7.933,
        -8.962,
        1,
        8.289,
        -8.962,
        8.644,
        -28.744,
        9,
        -29.943
      ]
    },
    {
      "Target": "Parameter",
      "Id": "ParamGunZ2",
      "Segments": [
        0,
        0,
        1,
        0.778,
        0.946,
        1.555,
        2.88,
        2.333,
        2.88,
        0,
        5.8,
        -1.44,
        1,
        6.867,
        -1.44,
        7.933,
        -1.314,
        9,
        -0.04
      ]
    },
    {
      "Target": "Parameter",
      "Id": "ParamArmR",
      "Segments": [
        0,
        0,
        1,
        0.633,
        0.974,
        1.267,
        8.327,
        1.9,
        8.327,
        0,
        6.2,
        -1.405,
        1,
        7.133,
        -1.405,
        8.067,
        -1.452,
        9,
        -0.051
      ]
    },
    {
      "Target": "Parameter",
      "Id": "ParamArmR1",
      "Segments": [
        0,
        0,
        1,
        0.544,
        -2.232,
        1.089,
        -17.023,
        1.633,
        -17.023,
        0,
        6.4,
        3.632,
        1,
        7.267,
        3.632,
        8.133,
        3.6,
        9,
        0.135
      ]
    },
    {
      "Target": "Parameter",
      "Id": "ParamHandR",
      "Segments": [
        0,
        0,
        0,
        1.367,
        -2.064,
        0,
        2.767,
        8.36,
        1,
        3.478,
        8.36,
        4.189,
        8.194,
        4.9,
        5.03,
        1,
        5.267,
        3.399,
        5.633,
        -11.791,
        6,
        -11.791,
        1,
        7,
        -11.791,
        8,
        -0.258,
        9,
        -0.004
      ]
    },
    {
      "Target": "Parameter",
      "Id": "ParamFingerR1",
      "Segments": [
        0,
        0,
        1,
        0.844,
        0.197,
        1.689,
        0.3,
        2.533,
        0.3,
        0,
        6.067,
        -0.341,
        1,
        7.045,
        -0.341,
        8.022,
        -0.233,
        9,
        -0.008
      ]
    },
    {
      "Target": "Parameter",
      "Id": "ParamLegL",
      "Segments": [
        0,
        30,
        0,
        3.2,
        21.209,
        1,
        5.133,
        21.209,
        7.067,
        29.9,
        9,
        29.999
      ]
    },
    {
      "Target": "Parameter",
      "Id": "ParamLegLY",
      "Segments": [
        0,
        0,
        0,
        2,
        -18.846,
        1,
        2.667,
        -18.846,
        3.333,
        -2.913,
        4,
        -2.139,
        1,
        5.667,
        -0.202,
        7.333,
        -0.003,
        9,
        0
      ]
    },
    {
      "Target": "Parameter",
      "Id": "ParamLegR",
      "Segments": [
        0,
        0,
        1,
        1,
        -8.863,
        2,
        -9.903,
        3,
        -9.903,
        0,
        5.133,
        23.604,
        1,
        6.422,
        23.604,
        7.711,
        11.728,
        9,
        0.296
      ]
    },
    {
      "Target": "Parameter",
      "Id": "ParamLegRY",
      "Segments": [
        0,
        0,
        1,
        0.6,
        0,
        1.2,
        -0.099,
        1.8,
        2.878,
        1,
        2.2,
        4.862,
        2.6,
        24.964,
        3,
        24.964,
        1,
        3.533,
        24.964,
        4.067,
        2.076,
        4.6,
        1.568,
        1,
        6.067,
        0.171,
        7.533,
        0.002,
        9,
        0
      ]
    },
    {
      "Target": "Parameter",
      "Id": "ParamOpaishakeX",
      "Segments": [
        0,
        0,
        1,
        0.322,
        -0.248,
        0.645,
        -0.4,
        0.967,
        -0.4,
        1,
        1.311,
        -0.4,
        1.656,
        -0.3,
        2,
        0,
        1,
        2.333,
        0.29,
        2.667,
        0.5,
        3,
        0.5,
        0,
        4,
        -0.2,
        1,
        4.211,
        -0.2,
        4.422,
        -0.172,
        4.633,
        0,
        1,
        4.966,
        0.272,
        5.3,
        0.5,
        5.633,
        0.5,
        0,
        6.633,
        -0.2,
        0,
        7.667,
        0.5,
        1,
        8.111,
        0.5,
        8.556,
        0.357,
        9,
        0.025
      ]
    },
    {
      "Target": "Parameter",
      "Id": "ParamOpaishakeX2",
      "Segments": [
        0,
        0,
        2,
        0.967,
        0,
        0,
        2.2,
        15.54,
        1,
        2.611,
        15.54,
        3.022,
        10.323,
        3.433,
        -5.904,
        1,
        3.666,
        -15.114,
        3.9,
        -24.417,
        4.133,
        -24.417,
        0,
        4.7,
        25.381,
        0,
        6.033,
        -15,
        0,
        7.333,
        5.585,
        1,
        7.889,
        5.585,
        8.444,
        0.217,
        9,
        0.006
      ]
    },
    {
      "Target": "Parameter",
      "Id": "ParamOpaishakeY",
      "Segments": [
        0,
        0,
        0,
        1,
        -0.4,
        1,
        1.333,
        -0.4,
        1.667,
        -0.375,
        2,
        0,
        1,
        2.211,
        0.238,
        2.422,
        1,
        2.633,
        1,
        0,
        3.4,
        -0.4,
        0,
        4.067,
        1,
        0,
        4.967,
        0,
        0,
        6.1,
        1,
        0,
        7.533,
        -0.4,
        1,
        8.022,
        -0.4,
        8.511,
        -0.018,
        9,
        -0.001
      ]
    },
    {
      "Target": "Parameter",
      "Id": "ParamOpaishakeY2",
      "Segments": [
        0,
        0,
        1,
        0.233,
        0,
        0.467,
        -0.415,
        0.7,
        2,
        1,
        1.067,
        5.794,
        1.433,
        14.468,
        1.8,
        14.468,
        0,
        3.067,
        -14,
        0,
        3.733,
        14.468,
        0,
        4.567,
        -14,
        0,
        5.967,
        4.038,
        0,
        6.733,
        -8.783,
        0,
        8.033,
        7.571,
        1,
        8.355,
        7.571,
        8.678,
        0.496,
        9,
        0.025
      ]
    },
    {
      "Target": "Parameter",
      "Id": "ParamHairFront",
      "Segments": [
        0,
        0,
        0,
        1.333,
        -0.454,
        0,
        3.267,
        0.508,
        0,
        5.4,
        -0.6,
        0,
        6.867,
        0.358,
        0,
        8.2,
        -0.278,
        1,
        8.467,
        -0.278,
        8.733,
        -0.022,
        9,
        -0.001
      ]
    },
    {
      "Target": "Parameter",
      "Id": "ParamHaiFrontY",
      "Segments": [
        0,
        0,
        0,
        0.933,
        -0.419,
        0,
        2.433,
        0.308,
        0,
        4.433,
        -0.5,
        0,
        6.1,
        0.576,
        0,
        7.733,
        -0.419,
        1,
        8.155,
        -0.419,
        8.578,
        -0.021,
        9,
        -0.001
      ]
    },
    {
      "Target": "Parameter",
      "Id": "ParamHairFront2",
      "Segments": [
        0,
        0,
        0,
        1.7,
        -0.486,
        0,
        3.7,
        0.534,
        0,
        5.433,
        -0.416,
        0,
        6.667,
        0.229,
        0,
        7.833,
        -0.25,
        1,
        8.222,
        -0.25,
        8.611,
        -0.014,
        9,
        -0.001
      ]
    },
    {
      "Target": "Parameter",
      "Id": "ParamHairFront2Y",
      "Segments": [
        0,
        0,
        0,
        1.167,
        -0.419,
        0,
        2.833,
        0.52,
        0,
        4.433,
        -0.5,
        0,
        6.267,
        0.52,
        0,
        8.2,
        -0.201,
        1,
        8.467,
        -0.201,
        8.733,
        -0.016,
        9,
        -0.001
      ]
    },
    {
      "Target": "Parameter",
      "Id": "ParamHairSide",
      "Segments": [
        0,
        0,
        0,
        0.933,
        0.291,
        0,
        2.233,
        -0.351,
        0,
        3.833,
        0.446,
        0,
        5.533,
        -0.521,
        0,
        7.467,
        0.291,
        1,
        7.978,
        0.291,
        8.489,
        0.012,
        9,
        0
      ]
    },
    {
      "Target": "Parameter",
      "Id": "ParamHairFrontY",
      "Segments": [
        0,
        0,
        1,
        0.222,
        0.118,
        0.445,
        0.315,
        0.667,
        0.315,
        0,
        1.8,
        -0.322,
        0,
        3.167,
        0.39,
        0,
        4.567,
        -0.464,
        0,
        6.533,
        0.39,
        0,
        8.1,
        -0.189,
        1,
        8.4,
        -0.189,
        8.7,
        -0.167,
        9,
        -0.017
      ]
    },
    {
      "Target": "Parameter",
      "Id": "ParamHairBack",
      "Segments": [
        0,
        0,
        1,
        0.644,
        -0.474,
        1.289,
        -0.619,
        1.933,
        -0.619,
        0,
        3.767,
        0.671,
        0,
        5.567,
        -0.619,
        0,
        7.567,
        0.671,
        1,
        8.045,
        0.671,
        8.522,
        0.374,
        9,
        0.024
      ]
    },
    {
      "Target": "Parameter",
      "Id": "ParamHairBackY",
      "Segments": [
        0,
        0,
        1,
        0.411,
        -0.281,
        0.822,
        -0.619,
        1.233,
        -0.619,
        0,
        2.933,
        0.671,
        0,
        4.7,
        -0.619,
        0,
        6.733,
        0.671,
        1,
        7.489,
        0.671,
        8.244,
        0.528,
        9,
        0.023
      ]
    },
    {
      "Target": "Parameter",
      "Id": "ParamHairBack2",
      "Segments": [
        0,
        0,
        1,
        0.333,
        -0.2,
        0.667,
        -0.5,
        1,
        -0.5,
        0,
        3,
        0.5,
        0,
        5.033,
        -0.351,
        0,
        7.033,
        0.5,
        1,
        7.689,
        0.5,
        8.344,
        0.403,
        9,
        0.02
      ]
    },
    {
      "Target": "Parameter",
      "Id": "ParamHairBack2Y",
      "Segments": [
        0,
        0,
        1,
        0.667,
        0.4,
        1.333,
        0.5,
        2,
        0.5,
        0,
        4,
        -0.351,
        0,
        6.033,
        0.5,
        0,
        8.033,
        -0.5,
        1,
        8.355,
        -0.5,
        8.678,
        -0.22,
        9,
        -0.02
      ]
    },
    {
      "Target": "Parameter",
      "Id": "ParamAngleX",
      "Segments": [
        0,
        0,
        1,
        0.567,
        4.03,
        1.133,
        6.348,
        1.7,
        7,
        1,
        2.556,
        7.984,
        3.411,
        8,
        4.267,
        8,
        0,
        6.433,
        -18,
        1,
        7.289,
        -18,
        8.144,
        -6.464,
        9,
        -0.24
      ]
    },
    {
      "Target": "Parameter",
      "Id": "ParamAngleY",
      "Segments": [
        0,
        0,
        1,
        0.567,
        -3.669,
        1.133,
        -15,
        1.7,
        -15,
        1,
        2.556,
        -15,
        3.411,
        -3.158,
        4.267,
        2,
        1,
        4.989,
        6.355,
        5.711,
        6,
        6.433,
        6,
        1,
        7.289,
        6,
        8.144,
        5.621,
        9,
        0.213
      ]
    },
    {
      "Target": "Parameter",
      "Id": "ParamBodyAngleX",
      "Segments": [
        0,
        0,
        1,
        0.522,
        -1.383,
        1.045,
        -3.813,
        1.567,
        -3.813,
        0,
        2.767,
        10,
        0,
        5.067,
        -7.921,
        0,
        6.9,
        7,
        1,
        7.6,
        7,
        8.3,
        4.157,
        9,
        0.19
      ]
    },
    {
      "Target": "Parameter",
      "Id": "ParamBodyAngleY",
      "Segments": [
        0,
        0,
        1,
        0.533,
        0.527,
        1.067,
        4.24,
        1.6,
        4.24,
        0,
        6.067,
        -1.02,
        1,
        7.045,
        -1.02,
        8.022,
        -0.979,
        9,
        -0.033
      ]
    },
    {
      "Target": "Parameter",
      "Id": "ParamBodyAngleZ",
      "Segments": [
        0,
        0,
        1,
        1.022,
        0.64,
        2.045,
        1.931,
        3.067,
        1.931,
        0,
        5.7,
        -0.714,
        1,
        6.8,
        -0.714,
        7.9,
        -0.696,
        9,
        -0.021
      ]
    },
    {
      "Target": "Parameter",
      "Id": "ParamBreath",
      "Segments": [
        0,
        0.5,
        0,
        1.633,
        0.186,
        0,
        3.233,
        0.5,
        0,
        4.633,
        0.115,
        0,
        6.367,
        0.5,
        0,
        8,
        0.037,
        1,
        8.333,
        0.037,
        8.667,
        0.471,
        9,
        0.499
      ]
    },
    {
      "Target": "Parameter",
      "Id": "ParamHipX",
      "Segments": [
        0,
        0,
        1,
        0.333,
        -1.967,
        0.667,
        -5,
        1,
        -5,
        1,
        1.333,
        -5,
        1.667,
        -3.333,
        2,
        0,
        1,
        2.333,
        3.333,
        2.667,
        5,
        3,
        5,
        1,
        3.333,
        5,
        3.667,
        3.333,
        4,
        0,
        1,
        4.333,
        -3.333,
        4.667,
        -5,
        5,
        -5,
        1,
        5.333,
        -5,
        5.667,
        -3.333,
        6,
        0,
        1,
        6.333,
        3.333,
        6.667,
        5,
        7,
        5,
        1,
        7.667,
        5,
        8.333,
        4.031,
        9,
        0.194
      ]
    },
    {
      "Target": "Parameter",
      "Id": "ParamHipY",
      "Segments": [
        0,
        0,
        1,
        0.656,
        3.444,
        1.311,
        4.174,
        1.967,
        4.174,
        1,
        2.311,
        4.174,
        2.656,
        3.072,
        3,
        0,
        1,
        3.333,
        -2.973,
        3.667,
        -5,
        4,
        -5,
        0,
        6.067,
        3.652,
        0,
        8,
        -5,
        1,
        8.333,
        -5,
        8.667,
        -2.012,
        9,
        -0.179
      ]
    },
    {
      "Target": "Model",
      "Id": "Opacity",
      "Segments": [
        0,
        1,
        0,
        9,
        1
      ]
    },
    {
      "Target": "Parameter",
      "Id": "ParamShengQiTX1",
      "Segments": [
        0,
        0,
        0,
        9,
        0
      ]
    },
    {
      "Target": "Parameter",
      "Id": "ParamShengQiOP1",
      "Segments": [
        0,
        -30,
        0,
        9,
        -30
      ]
    },
    {
      "Target": "Parameter",
      "Id": "ParamShengQiTX2",
      "Segments": [
        0,
        -30,
        0,
        9,
        -30
      ]
    },
    {
      "Target": "Parameter",
      "Id": "ParamShengQiOP2",
      "Segments": [
        0,
        -30,
        0,
        9,
        -30
      ]
    },
    {
      "Target": "Parameter",
      "Id": "ParamShengQiTX3",
      "Segments": [
        0,
        -30,
        0,
        9,
        -30
      ]
    },
    {
      "Target": "Parameter",
      "Id": "ParamShengQiOP3",
      "Segments": [
        0,
        -30,
        0,
        9,
        -30
      ]
    },
    {
      "Target": "Parameter",
      "Id": "ParamYinFu",
      "Segments": [
        0,
        0,
        0,
        9,
        0
      ]
    },
    {
      "Target": "Parameter",
      "Id": "ParamYFX",
      "Segments": [
        0,
        0,
        0,
        9,
        0
      ]
    },
    {
      "Target": "Parameter",
      "Id": "ParamYFY",
      "Segments": [
        0,
        0,
        0,
        9,
        0
      ]
    },
    {
      "Target": "Parameter",
      "Id": "ParamYinFuOpen",
      "Segments": [
        0,
        -30,
        0,
        9,
        -30
      ]
    },
    {
      "Target": "Parameter",
      "Id": "ParamYanJinX",
      "Segments": [
        0,
        0,
        0,
        9,
        0
      ]
    },
    {
      "Target": "Parameter",
      "Id": "ParamYanJingY",
      "Segments": [
        0,
        0,
        0,
        9,
        0
      ]
    },
    {
      "Target": "Parameter",
      "Id": "ParamYJZD",
      "Segments": [
        0,
        0,
        0,
        9,
        0
      ]
    },
    {
      "Target": "Parameter",
      "Id": "ParamYanJinOpen",
      "Segments": [
        0,
        -30,
        0,
        9,
        -30
      ]
    },
    {
      "Target": "Parameter",
      "Id": "ParamYanJingZD",
      "Segments": [
        0,
        30,
        0,
        9,
        30
      ]
    },
    {
      "Target": "Parameter",
      "Id": "ParamParamBrowLY",
      "Segments": [
        0,
        0,
        0,
        9,
        0
      ]
    },
    {
      "Target": "Parameter",
      "Id": "ParamFingerLQieHuan",
      "Segments": [
        0,
        -30,
        0,
        9,
        -30
      ]
    },
    {
      "Target": "Parameter",
      "Id": "ParamFingerL2",
      "Segments": [
        0,
        -30,
        0,
        9,
        -30
      ]
    },
    {
      "Target": "Parameter",
      "Id": "ParamFingerL3",
      "Segments": [
        0,
        0,
        0,
        9,
        0
      ]
    },
    {
      "Target": "Parameter",
      "Id": "ParamErJiXianDJ",
      "Segments": [
        0,
        -30,
        0,
        9,
        -30
      ]
    },
    {
      "Target": "Parameter",
      "Id": "ParamGUNX",
      "Segments": [
        0,
        0,
        0,
        9,
        0
      ]
    },
    {
      "Target": "Parameter",
      "Id": "ParamGUNY",
      "Segments": [
        0,
        0,
        0,
        9,
        0
      ]
    },
    {
      "Target": "Parameter",
      "Id": "ParamGunZ1",
      "Segments": [
        0,
        0,
        0,
        9,
        0
      ]
    },
    {
      "Target": "Parameter",
      "Id": "ParamGUNTY",
      "Segments": [
        0,
        -30,
        0,
        9,
        -30
      ]
    },
    {
      "Target": "Parameter",
      "Id": "ParamGUNz3",
      "Segments": [
        0,
        0,
        0,
        9,
        0
      ]
    },
    {
      "Target": "Parameter",
      "Id": "ParamFingerRQieHuan",
      "Segments": [
        0,
        -30,
        0,
        9,
        -30
      ]
    },
    {
      "Target": "Parameter",
      "Id": "ParamFingerR2",
      "Segments": [
        0,
        -30,
        0,
        9,
        -30
      ]
    },
    {
      "Target": "Parameter",
      "Id": "ParamFingerR3",
      "Segments": [
        0,
        0,
        0,
        9,
        0
      ]
    },
    {
      "Target": "Parameter",
      "Id": "ParamBlack0",
      "Segments": [
        0,
        0,
        0,
        9,
        0
      ]
    },
    {
      "Target": "Parameter",
      "Id": "ParamBLACKSHOW",
      "Segments": [
        0,
        0,
        0,
        9,
        0
      ]
    },
    {
      "Target": "Parameter",
      "Id": "ParamCamX",
      "Segments": [
        0,
        0,
        0,
        9,
        0
      ]
    },
    {
      "Target": "Parameter",
      "Id": "ParamCamY",
      "Segments": [
        0,
        0,
        0,
        9,
        0
      ]
    },
    {
      "Target": "Parameter",
      "Id": "ParamCAMup",
      "Segments": [
        0,
        0,
        0,
        9,
        0
      ]
    },
    {
      "Target": "Parameter",
      "Id": "ParamClothes",
      "Segments": [
        0,
        0,
        0,
        9,
        0
      ]
    },
    {
      "Target": "Parameter",
      "Id": "ParamClothesY",
      "Segments": [
        0,
        0,
        0,
        9,
        0
      ]
    },
    {
      "Target": "Parameter",
      "Id": "ParamClothes2",
      "Segments": [
        0,
        0,
        0,
        9,
        0
      ]
    },
    {
      "Target": "Parameter",
      "Id": "ParamClothes2Y",
      "Segments": [
        0,
        0,
        0,
        9,
        0
      ]
    },
    {
      "Target": "Parameter",
      "Id": "ParamMisk",
      "Segments": [
        0,
        0,
        0,
        9,
        0
      ]
    },
    {
      "Target": "Parameter",
      "Id": "ParamAngleZ",
      "Segments": [
        0,
        0,
        0,
        9,
        0
      ]
    },
    {
      "Target": "Parameter",
      "Id": "ParamCheek",
      "Segments": [
        0,
        0,
        0,
        9,
        0
      ]
    },
    {
      "Target": "Parameter",
      "Id": "ParamWX",
      "Segments": [
        0,
        0,
        0,
        9,
        0
      ]
    },
    {
      "Target": "Parameter",
      "Id": "ParamWY",
      "Segments": [
        0,
        0,
        0,
        9,
        0
      ]
    },
    {
      "Target": "Parameter",
      "Id": "ParamWZoom",
      "Segments": [
        0,
        0,
        0,
        9,
        0
      ]
    }
  ],
  "UserData": [
    {
      "Time": 0.0,
      "Value": ""
    }
  ]
}