{
  "Version": 3,
  "Meta": {
    "Duration": 10.67,
    "Fps": 30.0,
    "Loop": true,
    "AreBeziersRestricted": true,
    "CurveCount": 86,
    "TotalSegmentCount": 834,
    "TotalPointCount": 1340,
    "UserDataCount": 1,
    "TotalUserDataSize": 0
  },
  "Curves": [
    {
      "Target": "Parameter",
      "Id": "ParamAngleX",
      "Segments": [
        0,
        0,
        0,
        0.3,
        22.699,
        1,
        0.444,
        22.699,
        0.589,
        22.776,
        0.733,
        16.229,
        1,
        0.989,
        4.646,
        1.244,
        -9.847,
        1.5,
        -9.847,
        0,
        2.7,
        -6.302,
        2,
        5.433,
        -6.302,
        1,
        5.644,
        -6.302,
        5.856,
        -0.76,
        6.067,
        13.446,
        1,
        6.211,
        23.166,
        6.356,
        30,
        6.5,
        30,
        2,
        6.733,
        30,
        2,
        7.7,
        30,
        1,
        7.856,
        30,
        8.011,
        29.75,
        8.167,
        28.991,
        1,
        8.356,
        28.07,
        8.544,
        27.183,
        8.733,
        25.899,
        1,
        8.811,
        25.37,
        8.889,
        24.241,
        8.967,
        21.802,
        1,
        9.056,
        19.015,
        9.144,
        -30,
        9.233,
        -30,
        1,
        9.422,
        -30,
        9.611,
        -29.75,
        9.8,
        -23,
        1,
        10.089,
        -12.677,
        10.378,
        0,
        10.667,
        0
      ]
    },
    {
      "Target": "Parameter",
      "Id": "ParamAngleY",
      "Segments": [
        0,
        0,
        0,
        0.3,
        0.878,
        0,
        0.7,
        -8,
        0,
        1.433,
        -1.693,
        1,
        1.633,
        -1.693,
        1.833,
        -1.577,
        2.033,
        -4.438,
        1,
        2.2,
        -6.822,
        2.366,
        -20,
        2.533,
        -20,
        0,
        3.067,
        -1.693,
        2,
        5.433,
        -1.693,
        0,
        5.667,
        0,
        1,
        5.8,
        0,
        5.934,
        -8.633,
        6.067,
        -10.72,
        1,
        6.167,
        -12.285,
        6.267,
        -12.005,
        6.367,
        -12.005,
        1,
        6.489,
        -12.005,
        6.611,
        -7.855,
        6.733,
        -0.074,
        1,
        6.844,
        6.999,
        6.956,
        10.29,
        7.067,
        10.29,
        2,
        7.7,
        10.29,
        1,
        7.856,
        10.29,
        8.011,
        10.192,
        8.167,
        9.146,
        1,
        8.234,
        8.698,
        8.3,
        -8,
        8.367,
        -8,
        1,
        8.489,
        -8,
        8.611,
        -7.649,
        8.733,
        -3.994,
        1,
        8.811,
        -1.668,
        8.889,
        7.478,
        8.967,
        7.478,
        0,
        9.233,
        -3,
        0,
        9.8,
        7.478,
        0,
        10.667,
        0
      ]
    },
    {
      "Target": "Parameter",
      "Id": "ParamAngleZ",
      "Segments": [
        0,
        0,
        1,
        0.1,
        0,
        0.2,
        -0.105,
        0.3,
        0.168,
        1,
        0.456,
        0.592,
        0.611,
        14.495,
        0.767,
        14.495,
        1,
        1.056,
        14.495,
        1.344,
        -2.069,
        1.633,
        -7.836,
        1,
        2,
        -15.156,
        2.366,
        -15.537,
        2.733,
        -15.537,
        1,
        2.911,
        -15.537,
        3.089,
        0.363,
        3.267,
        6.921,
        1,
        3.411,
        12.249,
        3.556,
        11.988,
        3.7,
        11.988,
        1,
        4.278,
        11.988,
        4.855,
        11.187,
        5.433,
        8.861,
        1,
        5.511,
        8.548,
        5.589,
        2.842,
        5.667,
        0,
        1,
        5.845,
        -6.497,
        6.022,
        -9.589,
        6.2,
        -9.589,
        1,
        6.378,
        -9.589,
        6.555,
        -6.61,
        6.733,
        -2.482,
        1,
        6.822,
        -0.418,
        6.911,
        0,
        7,
        0,
        2,
        7.467,
        0,
        0,
        7.833,
        -15.537,
        0,
        8.167,
        -14.828,
        0,
        8.533,
        -28,
        1,
        8.6,
        -28,
        8.666,
        -28.088,
        8.733,
        -27.754,
        1,
        8.811,
        -27.364,
        8.889,
        -13.109,
        8.967,
        -13.109,
        0,
        9.233,
        -29,
        1,
        9.422,
        -29,
        9.611,
        -24.631,
        9.8,
        -17,
        1,
        10.089,
        -5.329,
        10.378,
        0,
        10.667,
        0
      ]
    },
    {
      "Target": "Parameter",
      "Id": "ParamEyeLOpen",
      "Segments": [
        0,
        1,
        0,
        0.333,
        0,
        0,
        0.767,
        1.01,
        2,
        2.367,
        1.01,
        0,
        2.633,
        0,
        0,
        2.867,
        1.01,
        0,
        4.167,
        0.684,
        0,
        5.433,
        1.01,
        0,
        5.667,
        1,
        2,
        5.9,
        1,
        2,
        6,
        1,
        0,
        6.133,
        0,
        2,
        6.2,
        0,
        0,
        6.433,
        1.02,
        0,
        6.567,
        0,
        1,
        6.622,
        0,
        6.678,
        0.872,
        6.733,
        0.88,
        1,
        6.911,
        0.906,
        7.089,
        0.91,
        7.267,
        0.91,
        2,
        7.7,
        0.91,
        0,
        8.167,
        1,
        0,
        8.367,
        0,
        0,
        8.533,
        1.5,
        0,
        8.967,
        0.935,
        2,
        9.8,
        0.935,
        0,
        10.667,
        1
      ]
    },
    {
      "Target": "Parameter",
      "Id": "ParamEyeROpen",
      "Segments": [
        0,
        1,
        0,
        0.333,
        0,
        0,
        0.767,
        1.01,
        2,
        2.367,
        1.01,
        0,
        2.633,
        0,
        0,
        2.867,
        1.01,
        0,
        4.167,
        0.7,
        0,
        5.433,
        1.01,
        0,
        5.667,
        1,
        2,
        5.9,
        1,
        2,
        6,
        1,
        0,
        6.133,
        0,
        2,
        6.2,
        0,
        0,
        6.433,
        0.89,
        0,
        6.567,
        0,
        1,
        6.622,
        0,
        6.678,
        0.788,
        6.733,
        0.82,
        1,
        6.911,
        0.923,
        7.089,
        0.94,
        7.267,
        0.94,
        2,
        7.7,
        0.94,
        0,
        8.167,
        1,
        0,
        8.367,
        0,
        0,
        8.533,
        1.5,
        0,
        8.967,
        0.956,
        2,
        9.8,
        0.956,
        0,
        10.667,
        1
      ]
    },
    {
      "Target": "Parameter",
      "Id": "ParamEyeSmile",
      "Segments": [
        0,
        0,
        2,
        0.333,
        0,
        2,
        0.9,
        0,
        2,
        3.133,
        0,
        2,
        5.433,
        0,
        2,
        5.667,
        0,
        1,
        6.022,
        0,
        6.378,
        0.13,
        6.733,
        0.311,
        1,
        6.911,
        0.402,
        7.089,
        0.42,
        7.267,
        0.42,
        2,
        7.7,
        0.42,
        0,
        8.967,
        0.305,
        2,
        9.8,
        0.305,
        0,
        10.667,
        0
      ]
    },
    {
      "Target": "Parameter",
      "Id": "ParamEyeBig",
      "Segments": [
        0,
        0,
        2,
        3.133,
        0,
        2,
        5.433,
        0,
        2,
        5.667,
        0,
        1,
        5.778,
        0,
        5.889,
        0.015,
        6,
        -0.1,
        1,
        6.156,
        -0.261,
        6.311,
        -0.6,
        6.467,
        -0.6,
        1,
        6.556,
        -0.6,
        6.644,
        -0.584,
        6.733,
        -0.516,
        1,
        6.9,
        -0.389,
        7.066,
        -0.3,
        7.233,
        -0.3,
        2,
        7.7,
        -0.3,
        2,
        8.367,
        -0.3,
        0,
        8.533,
        -0.7,
        0,
        8.967,
        -0.218,
        2,
        9.8,
        -0.218,
        0,
        10.667,
        0
      ]
    },
    {
      "Target": "Parameter",
      "Id": "ParamEyeBallX",
      "Segments": [
        0,
        0,
        1,
        0.578,
        0,
        1.155,
        -0.103,
        1.733,
        -0.177,
        1,
        2.544,
        -0.281,
        3.356,
        -0.3,
        4.167,
        -0.3,
        0,
        5.433,
        -0.177,
        0,
        5.667,
        -1,
        1,
        5.789,
        -1,
        5.911,
        -1.026,
        6.033,
        -0.626,
        1,
        6.189,
        -0.117,
        6.344,
        0.837,
        6.5,
        0.837,
        2,
        6.733,
        0.837,
        0,
        7.4,
        0.8,
        0,
        7.833,
        1,
        1,
        8.144,
        1,
        8.456,
        0.998,
        8.767,
        0.844,
        1,
        8.934,
        0.761,
        9.1,
        -0.3,
        9.267,
        -0.3,
        2,
        9.8,
        -0.3,
        0,
        10.667,
        0
      ]
    },
    {
      "Target": "Parameter",
      "Id": "ParamEyeBallY",
      "Segments": [
        0,
        0,
        2,
        3.133,
        0,
        0,
        4.167,
        -0.5,
        0,
        5.433,
        0,
        2,
        5.667,
        0,
        0,
        6.267,
        -0.58,
        2,
        6.6,
        -0.58,
        2,
        6.733,
        -0.58,
        0,
        7.4,
        -0.7,
        1,
        7.544,
        -0.7,
        7.689,
        -0.439,
        7.833,
        -0.367,
        1,
        8.144,
        -0.21,
        8.456,
        -0.187,
        8.767,
        -0.187,
        0,
        9.267,
        -0.2,
        2,
        9.8,
        -0.2,
        0,
        10.667,
        0
      ]
    },
    {
      "Target": "Parameter",
      "Id": "ParamBrowLY",
      "Segments": [
        0,
        0,
        1,
        0.244,
        0,
        0.489,
        0.115,
        0.733,
        0.214,
        1,
        0.933,
        0.295,
        1.133,
        0.36,
        1.333,
        0.392,
        1,
        1.589,
        0.433,
        1.844,
        0.437,
        2.1,
        0.437,
        0,
        3.133,
        -0.077,
        2,
        5.433,
        -0.077,
        1,
        5.511,
        -0.077,
        5.589,
        -0.12,
        5.667,
        0,
        1,
        5.856,
        0.292,
        6.044,
        1,
        6.233,
        1,
        0,
        6.733,
        0,
        0,
        7.267,
        0.16,
        2,
        7.7,
        0.16,
        0,
        8.767,
        0.116,
        2,
        9.8,
        0.116,
        0,
        10.667,
        0
      ]
    },
    {
      "Target": "Parameter",
      "Id": "ParamBrowRY",
      "Segments": [
        0,
        0,
        1,
        0.244,
        0,
        0.489,
        0.109,
        0.733,
        0.209,
        1,
        0.933,
        0.291,
        1.133,
        0.36,
        1.333,
        0.392,
        1,
        1.589,
        0.433,
        1.844,
        0.437,
        2.1,
        0.437,
        0,
        3.133,
        -0.074,
        2,
        5.433,
        -0.074,
        1,
        5.511,
        -0.074,
        5.589,
        -0.117,
        5.667,
        0,
        1,
        5.856,
        0.285,
        6.044,
        1,
        6.233,
        1,
        0,
        6.733,
        0,
        0,
        7.267,
        0.16,
        2,
        7.7,
        0.16,
        0,
        8.767,
        0.116,
        2,
        9.8,
        0.116,
        0,
        10.667,
        0
      ]
    },
    {
      "Target": "Parameter",
      "Id": "ParamBrowLForm",
      "Segments": [
        0,
        0,
        0,
        0.8,
        -0.57,
        1,
        0.922,
        -0.57,
        1.045,
        -0.377,
        1.167,
        -0.045,
        1,
        1.289,
        0.287,
        1.411,
        0.428,
        1.533,
        0.428,
        0,
        2.233,
        0,
        0,
        3,
        0.277,
        2,
        3.133,
        0.277,
        2,
        5.433,
        0.277,
        1,
        5.511,
        0.277,
        5.589,
        0.104,
        5.667,
        0,
        1,
        5.834,
        -0.224,
        6,
        -0.279,
        6.167,
        -0.279,
        0,
        6.567,
        0.55,
        1,
        6.622,
        0.55,
        6.678,
        0.204,
        6.733,
        -0.078,
        1,
        6.778,
        -0.304,
        6.822,
        -0.546,
        6.867,
        -0.56,
        1,
        7,
        -0.603,
        7.134,
        -0.61,
        7.267,
        -0.61,
        2,
        7.7,
        -0.61,
        0,
        8.767,
        -0.443,
        2,
        9.8,
        -0.443,
        0,
        10.667,
        0
      ]
    },
    {
      "Target": "Parameter",
      "Id": "ParamBrowRForm",
      "Segments": [
        0,
        0,
        0,
        0.8,
        -0.59,
        1,
        0.922,
        -0.59,
        1.045,
        -0.338,
        1.167,
        -0.006,
        1,
        1.289,
        0.326,
        1.411,
        0.429,
        1.533,
        0.429,
        0,
        2.233,
        0,
        0,
        3,
        0.272,
        2,
        3.133,
        0.272,
        2,
        5.433,
        0.272,
        1,
        5.511,
        0.272,
        5.589,
        0.106,
        5.667,
        0,
        1,
        5.834,
        -0.228,
        6,
        -0.286,
        6.167,
        -0.286,
        0,
        6.533,
        0.187,
        1,
        6.6,
        0.187,
        6.666,
        0.179,
        6.733,
        0.04,
        1,
        6.911,
        -0.331,
        7.089,
        -0.62,
        7.267,
        -0.62,
        2,
        7.7,
        -0.62,
        0,
        8.767,
        -0.451,
        2,
        9.8,
        -0.451,
        0,
        10.667,
        0
      ]
    },
    {
      "Target": "Parameter",
      "Id": "ParamMouthForm",
      "Segments": [
        0,
        0.5,
        2,
        3.467,
        0.5,
        0,
        4.867,
        0.1,
        2,
        5.433,
        0.1,
        0,
        5.667,
        0.4,
        0,
        6,
        -0.59,
        1,
        6.111,
        -0.59,
        6.222,
        -0.556,
        6.333,
        -0.48,
        1,
        6.455,
        -0.396,
        6.578,
        -0.35,
        6.7,
        -0.35,
        1,
        6.711,
        -0.35,
        6.722,
        -0.346,
        6.733,
        -0.353,
        1,
        6.844,
        -0.424,
        6.956,
        -0.49,
        7.067,
        -0.49,
        2,
        7.7,
        -0.49,
        0,
        8.067,
        -0.4,
        0,
        8.767,
        -0.8,
        1,
        9.111,
        -0.8,
        9.456,
        -0.67,
        9.8,
        -0.247,
        1,
        10.089,
        0.108,
        10.378,
        0.4,
        10.667,
        0.4
      ]
    },
    {
      "Target": "Parameter",
      "Id": "ParamMouthOpenY",
      "Segments": [
        0,
        0,
        2,
        3.367,
        0,
        1,
        3.867,
        0,
        4.367,
        0.392,
        4.867,
        0.393,
        2,
        5.433,
        0.393,
        1,
        5.511,
        0.396,
        5.589,
        -0.003,
        5.667,
        0,
        1,
        5.778,
        0.002,
        5.889,
        0.458,
        6,
        0.46,
        1,
        6.133,
        0.459,
        6.267,
        0.208,
        6.4,
        0.207,
        2,
        6.7,
        0.207,
        0,
        7.433,
        0,
        2,
        8.033,
        0,
        1,
        8.144,
        0,
        8.256,
        0.16,
        8.367,
        0.29,
        1,
        8.422,
        0.357,
        8.478,
        0.414,
        8.533,
        0.443,
        1,
        8.589,
        0.473,
        8.644,
        0.455,
        8.7,
        0.461,
        1,
        8.822,
        0.46,
        8.945,
        0.442,
        9.067,
        0.306,
        1,
        9.189,
        0.179,
        9.311,
        0,
        9.433,
        0,
        2,
        10.667,
        0
      ]
    },
    {
      "Target": "Parameter",
      "Id": "ParamMouthOpenX",
      "Segments": [
        0,
        1,
        0,
        0.5,
        -0.51,
        1,
        0.656,
        -0.51,
        0.811,
        -0.504,
        0.967,
        -0.455,
        1,
        1.2,
        -0.383,
        1.434,
        -0.24,
        1.667,
        -0.18,
        1,
        1.911,
        -0.118,
        2.156,
        -0.11,
        2.4,
        -0.11,
        2,
        3.133,
        -0.11,
        2,
        5.433,
        -0.11,
        0,
        5.667,
        0,
        0,
        6,
        -0.51,
        1,
        6.111,
        -0.51,
        6.222,
        -0.383,
        6.333,
        -0.24,
        1,
        6.466,
        -0.069,
        6.6,
        0.198,
        6.733,
        0.199,
        1,
        7.133,
        0.2,
        7.533,
        0.2,
        7.933,
        0.2,
        0,
        8.767,
        -0.8,
        0,
        9.833,
        0,
        2,
        10.667,
        0
      ]
    },
    {
      "Target": "Parameter",
      "Id": "ParamCheek",
      "Segments": [
        0,
        0,
        1,
        0.211,
        0,
        0.422,
        0.275,
        0.633,
        0.417,
        1,
        0.689,
        0.454,
        0.744,
        0.444,
        0.8,
        0.456,
        1,
        0.967,
        0.492,
        1.133,
        0.509,
        1.3,
        0.509,
        1,
        1.689,
        0.509,
        2.078,
        0.509,
        2.467,
        0.443,
        1,
        2.689,
        0.405,
        2.911,
        0.029,
        3.133,
        0.029,
        2,
        5.433,
        0.029,
        0,
        5.667,
        0,
        2,
        6.733,
        0,
        2,
        7.7,
        0,
        2,
        8.767,
        0,
        2,
        9.8,
        0,
        2,
        10.667,
        0
      ]
    },
    {
      "Target": "Parameter",
      "Id": "ParamJY",
      "Segments": [
        0,
        0,
        2,
        3.133,
        0,
        2,
        5.433,
        0,
        2,
        5.667,
        0,
        0,
        6.333,
        1,
        0,
        6.567,
        0.474,
        1,
        6.622,
        0.474,
        6.678,
        0.586,
        6.733,
        0.78,
        1,
        6.778,
        0.935,
        6.822,
        1,
        6.867,
        1,
        0,
        7.133,
        0.474,
        2,
        7.7,
        0.474,
        0,
        8.767,
        0.345,
        2,
        9.8,
        0.345,
        0,
        10.667,
        0
      ]
    },
    {
      "Target": "Parameter",
      "Id": "ParamBodyAngleX",
      "Segments": [
        0,
        0,
        0,
        1.4,
        -3.503,
        1,
        1.922,
        -3.503,
        2.445,
        -2.481,
        2.967,
        0.339,
        1,
        3.122,
        1.179,
        3.278,
        2.253,
        3.433,
        2.253,
        1,
        3.711,
        2.253,
        3.989,
        1.363,
        4.267,
        1.091,
        1,
        4.645,
        0.721,
        5.022,
        0.665,
        5.4,
        0.339,
        1,
        5.522,
        0.234,
        5.645,
        -1.834,
        5.767,
        -1.834,
        0,
        6.1,
        1.091,
        2,
        6.733,
        1.091,
        2,
        7.7,
        1.091,
        1,
        8.056,
        1.091,
        8.411,
        1.172,
        8.767,
        0.798,
        1,
        9.111,
        0.436,
        9.456,
        -10,
        9.8,
        -10,
        0,
        10.667,
        0
      ]
    },
    {
      "Target": "Parameter",
      "Id": "ParamBodyAngleY",
      "Segments": [
        0,
        0,
        0,
        0.733,
        2.728,
        0,
        2.133,
        -7,
        1,
        2.511,
        -7,
        2.889,
        -5.743,
        3.267,
        -5.725,
        1,
        3.456,
        -5.716,
        3.644,
        -5.72,
        3.833,
        -5.72,
        0,
        4.5,
        -7.652,
        1,
        4.8,
        -7.652,
        5.1,
        -7.663,
        5.4,
        -5.725,
        1,
        5.656,
        -4.073,
        5.911,
        0.681,
        6.167,
        0.681,
        2,
        6.733,
        0.681,
        2,
        7.7,
        0.681,
        1,
        7.878,
        0.681,
        8.055,
        0.574,
        8.233,
        0,
        1,
        8.289,
        -0.179,
        8.344,
        -2,
        8.4,
        -2,
        0,
        8.567,
        3,
        0,
        8.767,
        0.605,
        2,
        9.8,
        0.605,
        1,
        10.089,
        0.605,
        10.378,
        0.408,
        10.667,
        0
      ]
    },
    {
      "Target": "Parameter",
      "Id": "ParamBodyAngleZ",
      "Segments": [
        0,
        0,
        0,
        1.1,
        0.344,
        0,
        2.133,
        -3.141,
        2,
        5.4,
        -3.141,
        0,
        6,
        0.602,
        0,
        6.6,
        0,
        2,
        7.267,
        0,
        0,
        7.633,
        4.838,
        0,
        8.567,
        2,
        0,
        8.767,
        3.257,
        0,
        9.8,
        -2,
        0,
        10.667,
        0
      ]
    },
    {
      "Target": "Parameter",
      "Id": "ParamHipX",
      "Segments": [
        0,
        0,
        0,
        0.933,
        -0.1,
        1,
        1.5,
        -0.1,
        2.066,
        -0.007,
        2.633,
        0.1,
        1,
        3.022,
        0.173,
        3.411,
        0.185,
        3.8,
        0.185,
        1,
        4.322,
        0.185,
        4.845,
        0.16,
        5.367,
        0.076,
        1,
        5.5,
        0.055,
        5.634,
        0,
        5.767,
        0,
        0,
        6.167,
        0.37,
        2,
        6.733,
        0.37,
        2,
        7.7,
        0.37,
        1,
        8.056,
        0.37,
        8.411,
        0.385,
        8.767,
        0.306,
        1,
        9.111,
        0.229,
        9.456,
        -0.8,
        9.8,
        -0.8,
        0,
        10.667,
        0
      ]
    },
    {
      "Target": "Parameter",
      "Id": "ParamHipY",
      "Segments": [
        0,
        0,
        0,
        0.933,
        0.1,
        0,
        2.633,
        -0.4,
        0,
        4.5,
        -0.273,
        0,
        5.233,
        -0.446,
        0,
        5.867,
        0.1,
        0,
        6.267,
        -0.13,
        0,
        6.667,
        0,
        2,
        6.733,
        0,
        2,
        7.7,
        0,
        2,
        8.767,
        0,
        2,
        9.8,
        0,
        2,
        10.667,
        0
      ]
    },
    {
      "Target": "Parameter",
      "Id": "ParamLJian",
      "Segments": [
        0,
        0,
        2,
        1.067,
        0,
        2,
        5.433,
        0,
        2,
        5.667,
        0,
        0,
        6,
        -0.51,
        0,
        6.4,
        0.49,
        2,
        6.467,
        0.49,
        2,
        6.733,
        0.49,
        2,
        7.7,
        0.49,
        0,
        8.767,
        0.356,
        2,
        9.8,
        0.356,
        0,
        10.667,
        0
      ]
    },
    {
      "Target": "Parameter",
      "Id": "ParamLArm",
      "Segments": [
        0,
        0,
        2,
        5.433,
        0,
        2,
        5.667,
        0,
        0,
        6,
        -0.29,
        0,
        6.5,
        0.163,
        2,
        6.733,
        0.163,
        2,
        7.7,
        0.163,
        0,
        8.767,
        0.118,
        2,
        9.8,
        0.118,
        0,
        10.667,
        0
      ]
    },
    {
      "Target": "Parameter",
      "Id": "ParamLArmd",
      "Segments": [
        0,
        0,
        0,
        0.433,
        -0.424,
        0,
        1.067,
        0,
        2,
        5.433,
        0,
        2,
        5.667,
        0,
        0,
        6.033,
        0.199,
        1,
        6.122,
        0.199,
        6.211,
        0.158,
        6.3,
        0.05,
        1,
        6.433,
        -0.111,
        6.567,
        -0.206,
        6.7,
        -0.206,
        1,
        6.711,
        -0.206,
        6.722,
        -0.212,
        6.733,
        -0.203,
        1,
        6.911,
        -0.074,
        7.089,
        0.05,
        7.267,
        0.05,
        2,
        7.7,
        0.05,
        0,
        8.767,
        0.044,
        2,
        9.8,
        0.044,
        1,
        10.089,
        0.044,
        10.378,
        0.027,
        10.667,
        0
      ]
    },
    {
      "Target": "Parameter",
      "Id": "ParamLhandZ",
      "Segments": [
        0,
        0,
        0,
        0.433,
        -0.237,
        0,
        1.067,
        0,
        2,
        5.433,
        0,
        2,
        5.667,
        0,
        0,
        6.067,
        -0.596,
        0,
        6.7,
        0.496,
        2,
        6.733,
        0.496,
        2,
        7.7,
        0.496,
        0,
        8.767,
        0.373,
        2,
        9.8,
        0.373,
        1,
        10.089,
        0.373,
        10.378,
        0.039,
        10.667,
        0
      ]
    },
    {
      "Target": "Parameter",
      "Id": "ParamLZ1",
      "Segments": [
        0,
        0,
        2,
        1.067,
        0,
        2,
        5.433,
        0,
        2,
        5.667,
        0,
        1,
        6.022,
        0,
        6.378,
        6.977,
        6.733,
        15.421,
        1,
        6.844,
        18.06,
        6.956,
        18,
        7.067,
        18,
        2,
        7.7,
        18,
        0,
        8.767,
        13.081,
        2,
        9.8,
        13.081,
        0,
        10.667,
        0
      ]
    },
    {
      "Target": "Parameter",
      "Id": "ParamLZ2",
      "Segments": [
        0,
        0,
        0,
        0.367,
        -29.706,
        1,
        0.5,
        -29.706,
        0.634,
        -28.207,
        0.767,
        -15,
        1,
        0.867,
        -5.095,
        0.967,
        16,
        1.067,
        16,
        2,
        5.433,
        16,
        1,
        5.511,
        16,
        5.589,
        8.705,
        5.667,
        0,
        1,
        5.767,
        -11.192,
        5.867,
        -14.759,
        5.967,
        -14.759,
        0,
        6.367,
        0,
        1,
        6.489,
        0,
        6.611,
        -3.547,
        6.733,
        -12.31,
        1,
        6.889,
        -23.463,
        7.044,
        -30,
        7.2,
        -30,
        2,
        7.7,
        -30,
        0,
        8.767,
        -25.343,
        2,
        9.8,
        -25.343,
        1,
        10.089,
        -25.343,
        10.378,
        -12.221,
        10.667,
        0
      ]
    },
    {
      "Target": "Parameter",
      "Id": "ParamLZ3",
      "Segments": [
        0,
        0,
        2,
        5.433,
        0,
        2,
        5.667,
        0,
        0,
        6.1,
        -17.258,
        1,
        6.311,
        -17.258,
        6.522,
        -7.85,
        6.733,
        5.417,
        1,
        6.844,
        12.4,
        6.956,
        14,
        7.067,
        14,
        2,
        7.7,
        14,
        0,
        8.767,
        10.174,
        2,
        9.8,
        10.174,
        0,
        10.667,
        0
      ]
    },
    {
      "Target": "Parameter",
      "Id": "ParamLZ5",
      "Segments": [
        0,
        0,
        2,
        5.433,
        0,
        2,
        5.667,
        0,
        0,
        6.1,
        -20.979,
        1,
        6.311,
        -20.979,
        6.522,
        -5.651,
        6.733,
        16.002,
        1,
        6.844,
        27.399,
        6.956,
        30,
        7.067,
        30,
        2,
        7.7,
        30,
        0,
        8.767,
        21.802,
        2,
        9.8,
        21.802,
        0,
        10.667,
        0
      ]
    },
    {
      "Target": "Parameter",
      "Id": "ParamRArm",
      "Segments": [
        0,
        0,
        0,
        0.467,
        -0.4,
        0,
        0.9,
        -0.14,
        0,
        1.667,
        -1,
        0,
        2.833,
        0,
        2,
        4.067,
        0,
        2,
        5.433,
        0,
        2,
        6.767,
        0,
        2,
        7.133,
        0,
        0,
        7.5,
        -0.8,
        2,
        8.767,
        -0.8,
        1,
        9.111,
        -0.8,
        9.456,
        -0.811,
        9.8,
        -0.7,
        1,
        10.089,
        -0.607,
        10.378,
        0,
        10.667,
        0
      ]
    },
    {
      "Target": "Parameter",
      "Id": "ParamRArmX",
      "Segments": [
        0,
        0,
        2,
        1.667,
        0,
        0,
        2.4,
        -0.9,
        0,
        2.833,
        0,
        2,
        5.033,
        0,
        2,
        5.433,
        0,
        2,
        6.767,
        0,
        2,
        7.133,
        0,
        2,
        8.767,
        0,
        0,
        9.8,
        -1,
        1,
        10.089,
        -1,
        10.378,
        -0.288,
        10.667,
        0
      ]
    },
    {
      "Target": "Parameter",
      "Id": "ParamRArmd",
      "Segments": [
        0,
        0,
        0,
        0.5,
        0.332,
        0,
        0.9,
        0.18,
        0,
        1.667,
        0.72,
        0,
        2.4,
        0.1,
        0,
        3.6,
        0.293,
        2,
        5.433,
        0.293,
        2,
        6.7,
        0.293,
        0,
        7.433,
        0.7,
        2,
        8.767,
        0.7,
        0,
        9.8,
        1,
        0,
        10.667,
        0
      ]
    },
    {
      "Target": "Parameter",
      "Id": "ParamRArmdO",
      "Segments": [
        0,
        0,
        0,
        0.767,
        0.4,
        0,
        3.033,
        0,
        0,
        5.133,
        0.579,
        2,
        5.433,
        0.579,
        2,
        6.7,
        0.579,
        0,
        7.067,
        0.421,
        2,
        8.767,
        0.421,
        0,
        9.8,
        0.6,
        0,
        10.667,
        0
      ]
    },
    {
      "Target": "Parameter",
      "Id": "ParamRhandZ",
      "Segments": [
        0,
        0,
        0,
        0.5,
        -0.467,
        1,
        0.678,
        -0.467,
        0.855,
        -0.479,
        1.033,
        -0.202,
        1,
        1.322,
        0.249,
        1.611,
        0.837,
        1.9,
        0.837,
        0,
        2.833,
        -0.352,
        0,
        4.333,
        -0.271,
        2,
        5.433,
        -0.271,
        2,
        6.7,
        -0.271,
        0,
        7.433,
        -0.5,
        2,
        8.767,
        -0.5,
        2,
        9.8,
        -0.5,
        1,
        10.089,
        -0.5,
        10.378,
        -0.125,
        10.667,
        0
      ]
    },
    {
      "Target": "Parameter",
      "Id": "ParamRhandA",
      "Segments": [
        0,
        0,
        2,
        1.867,
        0,
        0,
        2.4,
        1,
        2,
        5.433,
        1,
        2,
        6.7,
        1,
        0,
        7.433,
        0,
        2,
        8.767,
        0,
        2,
        9.8,
        0,
        2,
        10.667,
        0
      ]
    },
    {
      "Target": "Parameter",
      "Id": "ParamHJAAA",
      "Segments": [
        0,
        0,
        2,
        1.667,
        0,
        2,
        4.933,
        0,
        0,
        5.433,
        1,
        2,
        6.7,
        1,
        2,
        7.433,
        1,
        2,
        8.767,
        1,
        2,
        9.8,
        1,
        0,
        10.667,
        0
      ]
    },
    {
      "Target": "Parameter",
      "Id": "ParamHJX",
      "Segments": [
        0,
        0,
        0,
        0.467,
        -24.073,
        0,
        0.7,
        -6,
        0,
        1.133,
        -18.024,
        1,
        1.311,
        -18.024,
        1.489,
        -15.356,
        1.667,
        0,
        1,
        1.811,
        12.477,
        1.956,
        30,
        2.1,
        30,
        2,
        5.333,
        30,
        2,
        5.433,
        30,
        2,
        6.7,
        30,
        0,
        7.167,
        24.808,
        2,
        8.767,
        24.808,
        2,
        9.8,
        24.808,
        1,
        10.089,
        24.808,
        10.378,
        10.117,
        10.667,
        -3
      ]
    },
    {
      "Target": "Parameter",
      "Id": "ParamHJB",
      "Segments": [
        0,
        0,
        2,
        1.667,
        0,
        2,
        2.4,
        0,
        1,
        2.678,
        0,
        2.955,
        0.414,
        3.233,
        0.517,
        1,
        3.755,
        0.712,
        4.278,
        0.76,
        4.8,
        0.942,
        1,
        4.978,
        1.004,
        5.155,
        1.5,
        5.333,
        1.5,
        2,
        5.433,
        1.5,
        2,
        6.7,
        1.5,
        0,
        7.167,
        1.09,
        2,
        8.767,
        1.09,
        2,
        9.8,
        1.09,
        0,
        10.667,
        0
      ]
    },
    {
      "Target": "Parameter",
      "Id": "ParamRhandB",
      "Segments": [
        0,
        0,
        2,
        1.833,
        0,
        0,
        2.467,
        1,
        2,
        5.433,
        1,
        0,
        5.667,
        0,
        2,
        6.733,
        0,
        2,
        7.7,
        0,
        2,
        8.767,
        0,
        2,
        9.8,
        0,
        2,
        10.667,
        0
      ]
    },
    {
      "Target": "Parameter",
      "Id": "ParamQP",
      "Segments": [
        0,
        0,
        2,
        1.833,
        0,
        0,
        2.467,
        1,
        0,
        2.9,
        0.951,
        0,
        3.433,
        1,
        0,
        4,
        0.951,
        0,
        4.4,
        1,
        0,
        4.9,
        0.951,
        0,
        5.433,
        1,
        0,
        5.667,
        0,
        2,
        6.733,
        0,
        2,
        7.7,
        0,
        2,
        8.767,
        0,
        2,
        9.8,
        0,
        2,
        10.667,
        0
      ]
    },
    {
      "Target": "Parameter",
      "Id": "ParamX",
      "Segments": [
        0,
        0,
        2,
        6.833,
        0,
        0,
        7.4,
        10.926,
        2,
        8.767,
        10.926,
        0,
        9.8,
        -30,
        1,
        9.856,
        -30,
        9.911,
        -2.594,
        9.967,
        -2.021,
        1,
        10.134,
        -0.301,
        10.3,
        0,
        10.467,
        0,
        2,
        10.667,
        0
      ]
    },
    {
      "Target": "Parameter",
      "Id": "Param4",
      "Segments": [
        0,
        0,
        2,
        5.433,
        0,
        2,
        6.033,
        0,
        0,
        6.833,
        -10,
        2,
        8.767,
        -10,
        0,
        9.8,
        -22,
        1,
        9.856,
        -22,
        9.911,
        -3.017,
        9.967,
        -2.354,
        1,
        10.134,
        -0.363,
        10.3,
        0,
        10.467,
        0,
        2,
        10.667,
        0
      ]
    },
    {
      "Target": "Parameter",
      "Id": "Param5",
      "Segments": [
        0,
        0,
        2,
        5.433,
        0,
        2,
        6.033,
        0,
        0,
        6.733,
        -21,
        2,
        8.767,
        -21,
        2,
        9.8,
        -21,
        1,
        9.867,
        -21,
        9.933,
        -3.577,
        10,
        -2.593,
        1,
        10.156,
        -0.296,
        10.311,
        0,
        10.467,
        0,
        2,
        10.667,
        0
      ]
    },
    {
      "Target": "Parameter",
      "Id": "Param6",
      "Segments": [
        0,
        0,
        2,
        5.6,
        0,
        0,
        6.967,
        18.765,
        2,
        8.767,
        18.765,
        0,
        9.8,
        23,
        1,
        9.867,
        23,
        9.933,
        4.217,
        10,
        3.061,
        1,
        10.156,
        0.366,
        10.311,
        0,
        10.467,
        0,
        2,
        10.667,
        0
      ]
    },
    {
      "Target": "Parameter",
      "Id": "ParamXAB",
      "Segments": [
        0,
        0,
        2,
        5.433,
        0,
        1,
        5.9,
        0,
        6.366,
        20.197,
        6.833,
        21,
        1,
        7.5,
        22.148,
        8.166,
        22.092,
        8.833,
        23.086,
        1,
        9.155,
        23.567,
        9.478,
        30,
        9.8,
        30,
        0,
        10.467,
        0,
        2,
        10.667,
        0
      ]
    },
    {
      "Target": "Parameter",
      "Id": "Param7",
      "Segments": [
        0,
        0,
        2,
        9.433,
        0,
        0,
        9.8,
        30,
        2,
        10.167,
        30,
        0,
        10.667,
        0
      ]
    },
    {
      "Target": "Parameter",
      "Id": "ParamHairFronto",
      "Segments": [
        0,
        0,
        0,
        0.767,
        -1,
        0,
        1.267,
        0.138,
        1,
        1.422,
        0.138,
        1.578,
        -0.455,
        1.733,
        -0.718,
        1,
        1.9,
        -1,
        2.066,
        -1,
        2.233,
        -1,
        0,
        3.033,
        0.59,
        0,
        3.433,
        0,
        0,
        4.033,
        0.898,
        1,
        4.2,
        0.898,
        4.366,
        0.648,
        4.533,
        0.043,
        1,
        4.666,
        -0.441,
        4.8,
        -0.744,
        4.933,
        -0.744,
        0,
        6.033,
        0.761,
        0,
        6.833,
        -0.744,
        0,
        7.7,
        0.761,
        0,
        8.8,
        -0.744,
        0,
        10.1,
        0.581,
        1,
        10.289,
        0.581,
        10.478,
        0.119,
        10.667,
        0
      ]
    },
    {
      "Target": "Parameter",
      "Id": "ParamHairBacko",
      "Segments": [
        0,
        0,
        0,
        0.867,
        -0.895,
        0,
        1.5,
        0.169,
        0,
        2.2,
        -0.895,
        0,
        3.033,
        0.457,
        0,
        3.433,
        0,
        0,
        4.2,
        0.912,
        1,
        4.333,
        0.912,
        4.467,
        0.853,
        4.6,
        0.43,
        1,
        4.789,
        -0.169,
        4.978,
        -0.726,
        5.167,
        -0.726,
        0,
        6.3,
        0.789,
        0,
        7.067,
        -0.726,
        0,
        7.967,
        0.789,
        1,
        8.322,
        0.789,
        8.678,
        -0.531,
        9.033,
        -0.823,
        1,
        9.311,
        -1.051,
        9.589,
        -1,
        9.867,
        -1,
        1,
        10.134,
        -1,
        10.4,
        -0.207,
        10.667,
        0
      ]
    },
    {
      "Target": "Parameter",
      "Id": "ParamTRE1",
      "Segments": [
        0,
        0,
        0,
        2.2,
        -7.833,
        1,
        2.611,
        -7.833,
        3.022,
        -5.85,
        3.433,
        0,
        1,
        3.7,
        3.795,
        3.966,
        7.019,
        4.233,
        7.019,
        0,
        5.833,
        -7.833,
        0,
        7.6,
        7.019,
        0,
        9.667,
        -7.833,
        1,
        10,
        -7.833,
        10.334,
        -5.482,
        10.667,
        0
      ]
    },
    {
      "Target": "Parameter",
      "Id": "ParamTRE2",
      "Segments": [
        0,
        0,
        0,
        0.8,
        4.471,
        0,
        2.167,
        -5.036,
        0,
        3.067,
        2.645,
        1,
        3.189,
        2.645,
        3.311,
        1.45,
        3.433,
        0,
        1,
        3.666,
        -2.768,
        3.9,
        -3.803,
        4.133,
        -3.803,
        0,
        5.2,
        5.961,
        0,
        7,
        -6.892,
        1,
        7.467,
        -6.892,
        7.933,
        -1.3,
        8.4,
        4.351,
        1,
        8.7,
        7.984,
        9,
        8.321,
        9.3,
        8.321,
        1,
        9.756,
        8.321,
        10.211,
        5.329,
        10.667,
        0
      ]
    },
    {
      "Target": "Parameter",
      "Id": "ParamH1",
      "Segments": [
        0,
        0,
        0,
        0.5,
        -0.603,
        0,
        0.9,
        0.735,
        0,
        1.567,
        -1,
        0,
        2.133,
        0.437,
        0,
        2.7,
        -0.806,
        1,
        2.944,
        -0.806,
        3.189,
        -0.626,
        3.433,
        0,
        1,
        3.522,
        0.228,
        3.611,
        0.627,
        3.7,
        0.627,
        0,
        4.167,
        -0.838,
        1,
        4.278,
        -0.838,
        4.389,
        -0.596,
        4.5,
        -0.134,
        1,
        4.633,
        0.421,
        4.767,
        0.688,
        4.9,
        0.688,
        1,
        5.056,
        0.688,
        5.211,
        0.163,
        5.367,
        -0.411,
        1,
        5.5,
        -0.903,
        5.634,
        -1,
        5.767,
        -1,
        1,
        6,
        -1,
        6.234,
        -1.024,
        6.467,
        -0.865,
        1,
        6.678,
        -0.721,
        6.889,
        0.512,
        7.1,
        0.512,
        0,
        7.467,
        -0.13,
        0,
        8.433,
        0.989,
        0,
        9.233,
        0,
        0,
        9.6,
        0.56,
        0,
        10.3,
        -0.218,
        1,
        10.422,
        -0.218,
        10.545,
        -0.007,
        10.667,
        0
      ]
    },
    {
      "Target": "Parameter",
      "Id": "ParamH1o",
      "Segments": [
        0,
        0,
        0,
        0.5,
        0.769,
        0,
        1.167,
        -0.731,
        0,
        1.867,
        0.858,
        0,
        2.433,
        -0.55,
        1,
        2.5,
        -0.55,
        2.566,
        -0.582,
        2.633,
        -0.436,
        1,
        2.778,
        -0.12,
        2.922,
        0.388,
        3.067,
        0.388,
        0,
        3.433,
        0,
        0,
        3.767,
        0.689,
        0,
        4.267,
        -0.863,
        0,
        4.933,
        0.448,
        0,
        5.5,
        -0.863,
        1,
        5.622,
        -0.863,
        5.745,
        -0.514,
        5.867,
        -0.099,
        1,
        6.056,
        0.542,
        6.244,
        0.76,
        6.433,
        0.76,
        0,
        6.867,
        -0.612,
        0,
        7.4,
        0.63,
        0,
        8.033,
        0.13,
        0,
        8.633,
        1,
        0,
        9.333,
        -0.29,
        1,
        9.622,
        -0.29,
        9.911,
        -0.259,
        10.2,
        -0.173,
        1,
        10.356,
        -0.127,
        10.511,
        -0.039,
        10.667,
        0
      ]
    },
    {
      "Target": "Parameter",
      "Id": "ParamC1",
      "Segments": [
        0,
        0,
        0,
        0.567,
        -0.571,
        0,
        1,
        0.683,
        0,
        1.633,
        -1,
        0,
        2.167,
        0.378,
        0,
        2.7,
        -0.736,
        0,
        3.433,
        0,
        0,
        4.133,
        -1,
        1,
        4.266,
        -1,
        4.4,
        -0.79,
        4.533,
        -0.296,
        1,
        4.7,
        0.322,
        4.866,
        0.672,
        5.033,
        0.672,
        0,
        5.833,
        -1,
        1,
        6.011,
        -1,
        6.189,
        -0.908,
        6.367,
        -0.432,
        1,
        6.556,
        0.074,
        6.744,
        0.571,
        6.933,
        0.571,
        0,
        7.6,
        -0.093,
        1,
        7.756,
        -0.093,
        7.911,
        0.091,
        8.067,
        0.42,
        1,
        8.256,
        0.819,
        8.444,
        1,
        8.633,
        1,
        1,
        8.811,
        1,
        8.989,
        0.238,
        9.167,
        0.04,
        1,
        9.545,
        -0.381,
        9.922,
        -0.437,
        10.3,
        -0.437,
        1,
        10.422,
        -0.437,
        10.545,
        -0.094,
        10.667,
        0
      ]
    },
    {
      "Target": "Parameter",
      "Id": "ParamC1o",
      "Segments": [
        0,
        0,
        0,
        0.5,
        -0.704,
        0,
        0.9,
        0.257,
        0,
        1.333,
        -0.801,
        0,
        1.967,
        0.92,
        1,
        2.1,
        0.92,
        2.234,
        0.044,
        2.367,
        -0.341,
        1,
        2.556,
        -0.887,
        2.744,
        -0.934,
        2.933,
        -0.934,
        1,
        3.1,
        -0.934,
        3.266,
        -0.627,
        3.433,
        0,
        1,
        3.533,
        0.376,
        3.633,
        0.57,
        3.733,
        0.57,
        0,
        4.367,
        -0.634,
        1,
        4.489,
        -0.634,
        4.611,
        -0.458,
        4.733,
        -0.082,
        1,
        4.811,
        0.157,
        4.889,
        0.29,
        4.967,
        0.29,
        0,
        5.567,
        -0.552,
        1,
        5.7,
        -0.552,
        5.834,
        -0.531,
        5.967,
        -0.152,
        1,
        6.078,
        0.163,
        6.189,
        0.805,
        6.3,
        0.805,
        0,
        6.767,
        -0.393,
        0,
        7.467,
        0.694,
        0,
        8.033,
        0.194,
        0,
        8.633,
        1,
        0,
        9.233,
        0,
        2,
        10.667,
        0
      ]
    },
    {
      "Target": "Parameter",
      "Id": "ParamC2",
      "Segments": [
        0,
        0,
        0,
        0.7,
        -0.598,
        0,
        1.1,
        0.69,
        0,
        1.7,
        -0.99,
        0,
        2.333,
        0.277,
        0,
        2.8,
        -0.734,
        0,
        3.433,
        0,
        0,
        4.033,
        -0.73,
        1,
        4.2,
        -0.73,
        4.366,
        -0.514,
        4.533,
        -0.099,
        1,
        4.733,
        0.399,
        4.933,
        0.639,
        5.133,
        0.639,
        0,
        5.9,
        -0.994,
        0,
        6.1,
        0.76,
        0,
        6.633,
        -0.55,
        1,
        6.889,
        -0.55,
        7.144,
        -0.137,
        7.4,
        0.33,
        1,
        7.689,
        0.857,
        7.978,
        1,
        8.267,
        1,
        0,
        9.233,
        0,
        2,
        10.667,
        0
      ]
    },
    {
      "Target": "Parameter",
      "Id": "ParamC2o",
      "Segments": [
        0,
        0,
        0,
        0.9,
        -0.547,
        0,
        1.767,
        0.81,
        0,
        2.567,
        -0.855,
        1,
        2.856,
        -0.855,
        3.144,
        -0.628,
        3.433,
        0,
        1,
        3.578,
        0.314,
        3.722,
        0.59,
        3.867,
        0.59,
        0,
        4.433,
        -0.53,
        0,
        5.067,
        0.309,
        0,
        5.633,
        -0.544,
        1,
        5.744,
        -0.544,
        5.856,
        -0.561,
        5.967,
        -0.266,
        1,
        6.089,
        0.058,
        6.211,
        0.79,
        6.333,
        0.79,
        0,
        6.833,
        -0.616,
        0,
        7.6,
        0.517,
        0,
        8,
        -0.02,
        0,
        8.733,
        1,
        1,
        8.9,
        1,
        9.066,
        0.092,
        9.233,
        0,
        1,
        9.578,
        -0.19,
        9.922,
        -0.201,
        10.267,
        -0.201,
        1,
        10.4,
        -0.201,
        10.534,
        -0.046,
        10.667,
        0
      ]
    },
    {
      "Target": "Parameter",
      "Id": "ParamH2",
      "Segments": [
        0,
        0,
        0,
        0.7,
        -0.548,
        0,
        1.033,
        0.724,
        0,
        1.667,
        -0.937,
        0,
        2.2,
        0.459,
        0,
        2.7,
        -0.531,
        1,
        2.944,
        -0.531,
        3.189,
        -0.456,
        3.433,
        0,
        1,
        3.555,
        0.228,
        3.678,
        0.808,
        3.8,
        0.808,
        0,
        4.267,
        -0.757,
        1,
        4.4,
        -0.757,
        4.534,
        -0.43,
        4.667,
        0.039,
        1,
        4.811,
        0.547,
        4.956,
        0.727,
        5.1,
        0.727,
        1,
        5.233,
        0.727,
        5.367,
        0.184,
        5.5,
        -0.352,
        1,
        5.633,
        -0.888,
        5.767,
        -0.993,
        5.9,
        -0.993,
        0,
        6.133,
        0.85,
        0,
        6.5,
        -0.7,
        0,
        6.933,
        0.42,
        0,
        7.467,
        -0.129,
        0,
        8.733,
        1,
        0,
        9.233,
        0,
        2,
        10.667,
        0
      ]
    },
    {
      "Target": "Parameter",
      "Id": "ParamH2o",
      "Segments": [
        0,
        0,
        0,
        0.7,
        0.791,
        0,
        1.3,
        -0.636,
        0,
        2,
        0.848,
        1,
        2.133,
        0.848,
        2.267,
        0.109,
        2.4,
        -0.388,
        1,
        2.5,
        -0.761,
        2.6,
        -0.754,
        2.7,
        -0.754,
        1,
        2.944,
        -0.754,
        3.189,
        -0.57,
        3.433,
        0,
        1,
        3.589,
        0.363,
        3.744,
        0.69,
        3.9,
        0.69,
        0,
        4.367,
        -0.866,
        0,
        5.033,
        0.46,
        0,
        5.6,
        -0.854,
        1,
        5.778,
        -0.854,
        5.955,
        -0.799,
        6.133,
        -0.306,
        1,
        6.244,
        0.002,
        6.356,
        0.75,
        6.467,
        0.75,
        0,
        6.933,
        -1,
        0,
        7.6,
        0.643,
        0,
        8.133,
        0.08,
        0,
        8.733,
        0.906,
        0,
        9.5,
        -0.257,
        1,
        9.756,
        -0.257,
        10.011,
        -0.257,
        10.267,
        -0.251,
        1,
        10.4,
        -0.248,
        10.534,
        -0.055,
        10.667,
        0
      ]
    },
    {
      "Target": "Parameter",
      "Id": "ParamH3",
      "Segments": [
        0,
        0,
        0,
        0.267,
        0.27,
        0,
        0.767,
        -0.59,
        0,
        1.133,
        0.755,
        0,
        1.9,
        -0.937,
        0,
        2.467,
        0.493,
        0,
        3.433,
        0,
        0,
        3.9,
        0.802,
        0,
        4.4,
        -0.718,
        1,
        4.522,
        -0.718,
        4.645,
        -0.425,
        4.767,
        0.008,
        1,
        4.911,
        0.52,
        5.056,
        0.714,
        5.2,
        0.714,
        1,
        5.333,
        0.714,
        5.467,
        0.18,
        5.6,
        -0.348,
        1,
        5.733,
        -0.876,
        5.867,
        -0.98,
        6,
        -0.98,
        0,
        6.2,
        0.81,
        0,
        6.867,
        -0.583,
        0,
        8.367,
        0.966,
        0,
        9.233,
        0,
        0,
        10.167,
        0.455,
        0,
        10.667,
        0
      ]
    },
    {
      "Target": "Parameter",
      "Id": "ParamH3o",
      "Segments": [
        0,
        0,
        0,
        0.7,
        0.712,
        0,
        1.367,
        -0.624,
        0,
        2.033,
        0.778,
        1,
        2.178,
        0.778,
        2.322,
        0.185,
        2.467,
        -0.292,
        1,
        2.634,
        -0.842,
        2.8,
        -0.934,
        2.967,
        -0.934,
        1,
        3.122,
        -0.934,
        3.278,
        -0.478,
        3.433,
        0,
        1,
        3.611,
        0.546,
        3.789,
        0.681,
        3.967,
        0.681,
        1,
        4.034,
        0.681,
        4.1,
        0.362,
        4.167,
        -0.071,
        1,
        4.256,
        -0.649,
        4.344,
        -0.858,
        4.433,
        -0.858,
        0,
        5.133,
        0.451,
        0,
        5.7,
        -0.858,
        0,
        6.433,
        0.92,
        0,
        7,
        -0.92,
        0,
        7.667,
        0.67,
        0,
        8.3,
        -0.13,
        0,
        8.9,
        1,
        0,
        9.567,
        -0.378,
        1,
        9.8,
        -0.378,
        10.034,
        -0.263,
        10.267,
        -0.144,
        1,
        10.4,
        -0.076,
        10.534,
        -0.051,
        10.667,
        0
      ]
    },
    {
      "Target": "Model",
      "Id": "Opacity",
      "Segments": [
        0,
        1,
        0,
        10.67,
        1
      ]
    },
    {
      "Target": "Parameter",
      "Id": "ParamZJP1",
      "Segments": [
        0,
        0,
        0,
        10.67,
        0
      ]
    },
    {
      "Target": "Parameter",
      "Id": "ParamZJP2",
      "Segments": [
        0,
        0,
        0,
        10.67,
        0
      ]
    },
    {
      "Target": "Parameter",
      "Id": "ParamRLeg",
      "Segments": [
        0,
        0,
        0,
        10.67,
        0
      ]
    },
    {
      "Target": "Parameter",
      "Id": "ParamRFoot",
      "Segments": [
        0,
        0,
        0,
        10.67,
        0
      ]
    },
    {
      "Target": "Parameter",
      "Id": "ParamLarmdA",
      "Segments": [
        0,
        0,
        0,
        10.67,
        0
      ]
    },
    {
      "Target": "Parameter",
      "Id": "ParamLhandA",
      "Segments": [
        0,
        0,
        0,
        10.67,
        0
      ]
    },
    {
      "Target": "Parameter",
      "Id": "ParamRJian",
      "Segments": [
        0,
        0,
        0,
        10.67,
        0
      ]
    },
    {
      "Target": "Parameter",
      "Id": "ParamHJZ",
      "Segments": [
        0,
        0,
        0,
        10.67,
        0
      ]
    },
    {
      "Target": "Parameter",
      "Id": "ParamY",
      "Segments": [
        0,
        0,
        0,
        10.67,
        0
      ]
    },
    {
      "Target": "Parameter",
      "Id": "ParamO",
      "Segments": [
        0,
        0,
        0,
        10.67,
        0
      ]
    },
    {
      "Target": "Parameter",
      "Id": "Param",
      "Segments": [
        0,
        0,
        0,
        10.67,
        0
      ]
    },
    {
      "Target": "Parameter",
      "Id": "Param2",
      "Segments": [
        0,
        0,
        0,
        10.67,
        0
      ]
    },
    {
      "Target": "Parameter",
      "Id": "Param3",
      "Segments": [
        0,
        0,
        0,
        10.67,
        0
      ]
    },
    {
      "Target": "Parameter",
      "Id": "ParamQz1",
      "Segments": [
        0,
        0,
        0,
        10.67,
        0
      ]
    },
    {
      "Target": "Parameter",
      "Id": "ParamQz2",
      "Segments": [
        0,
        0,
        0,
        10.67,
        0
      ]
    },
    {
      "Target": "Parameter",
      "Id": "ParamYb1",
      "Segments": [
        0,
        0,
        0,
        10.67,
        0
      ]
    },
    {
      "Target": "Parameter",
      "Id": "ParamYb2",
      "Segments": [
        0,
        0,
        0,
        10.67,
        0
      ]
    },
    {
      "Target": "Parameter",
      "Id": "ParamPDD1",
      "Segments": [
        0,
        0,
        0,
        10.67,
        0
      ]
    },
    {
      "Target": "Parameter",
      "Id": "ParamPDD2",
      "Segments": [
        0,
        0,
        0,
        10.67,
        0
      ]
    },
    {
      "Target": "Parameter",
      "Id": "ParamRuX",
      "Segments": [
        0,
        0,
        0,
        10.67,
        0
      ]
    },
    {
      "Target": "Parameter",
      "Id": "ParamRuY",
      "Segments": [
        0,
        0,
        0,
        10.67,
        0
      ]
    },
    {
      "Target": "Parameter",
      "Id": "ParamRuX2",
      "Segments": [
        0,
        0,
        0,
        10.67,
        0
      ]
    },
    {
      "Target": "Parameter",
      "Id": "ParamRuY2",
      "Segments": [
        0,
        0,
        0,
        10.67,
        0
      ]
    }
  ],
  "UserData": [
    {
      "Time": 0.0,
      "Value": ""
    }
  ]
}